{
    "profile": {
      "image_32": "https://.../avatar/e3b51ca72dee4ef87916ae2b9240df50.jpg",
      "status_emoji": ":books:",
      "image_24": "https://.../avatar/e3b51ca72dee4ef87916ae2b9240df50.jpg",
      "image_192": "https://.../avatar/e3b51ca72dee4ef87916ae2b9240df50.jpg",
      "real_name": "Egon Spengler",
      "image_48": "https://.../avatar/e3b51ca72dee4ef87916ae2b9240df50.jpg",
      "team": "T012AB3C4",
      "display_name": "spengler",
      "status_expiration": 0,
      "real_name_normalized": "Egon Spengler",
      "status_text": "Print is dead",
      "avatar_hash": "ge3b51ca72de",
      "image_72": "https://.../avatar/e3b51ca72dee4ef87916ae2b9240df50.jpg",
      "email": "spengler@ghostbusters.example.com",
      "image_512": "https://.../avatar/e3b51ca72dee4ef87916ae2b9240df50.jpg",
      "display_name_normalized": "spengler"
    },
    "ok": true
}